{
  "image_index": 187,
  "objects": [
    {
      "size": "medium",
      "pixel_coords": [
        84,
        72,
        28.401376724243164
      ],
      "material": "metal",
      "3d_coords": [
        -6.910101890563965,
        -3.3630623817443848,
        0.5
      ],
      "group": [
        [
          -6.910101723755579,
          -3.363062498333426
        ],
        [
          -2.9308833946705835,
          -3.0033358859358543
        ],
        [
          1.0625799202775559,
          -2.8775086299201633
        ],
        [
          4.949854119165076,
          -3.800915933798797
        ]
      ],
      "rotation": 332.502972391271,
      "color": "brown",
      "shape": "cube"
    },
    {
      "size": "mini",
      "pixel_coords": [
        107,
        106,
        26.53607177734375
      ],
      "material": "rubber",
      "3d_coords": [
        -2.9308834075927734,
        -3.003335952758789,
        0.25
      ],
      "group": [
        [
          -6.910101723755579,
          -3.363062498333426
        ],
        [
          -2.9308833946705835,
          -3.0033358859358543
        ],
        [
          1.0625799202775559,
          -2.8775086299201633
        ],
        [
          4.949854119165076,
          -3.800915933798797
        ]
      ],
      "rotation": 237.200167085575,
      "color": "red",
      "shape": "sphere"
    },
    {
      "size": "large",
      "pixel_coords": [
        130,
        140,
        24.04402732849121
      ],
      "material": "metal",
      "3d_coords": [
        1.062579870223999,
        -2.8775086402893066,
        0.699999988079071
      ],
      "group": [
        [
          -6.910101723755579,
          -3.363062498333426
        ],
        [
          -2.9308833946705835,
          -3.0033358859358543
        ],
        [
          1.0625799202775559,
          -2.8775086299201633
        ],
        [
          4.949854119165076,
          -3.800915933798797
        ]
      ],
      "rotation": 307.1345792872733,
      "color": "red",
      "shape": "cylinder"
    },
    {
      "size": "small",
      "pixel_coords": [
        143,
        194,
        21.940324783325195
      ],
      "material": "rubber",
      "3d_coords": [
        4.949853897094727,
        -3.8009159564971924,
        0.3499999940395355
      ],
      "group": [
        [
          -6.910101723755579,
          -3.363062498333426
        ],
        [
          -2.9308833946705835,
          -3.0033358859358543
        ],
        [
          1.0625799202775559,
          -2.8775086299201633
        ],
        [
          4.949854119165076,
          -3.800915933798797
        ]
      ],
      "rotation": 330.9237232049184,
      "color": "brown",
      "shape": "sphere"
    },
    {
      "size": "mini",
      "pixel_coords": [
        90,
        73,
        28.658538818359375
      ],
      "material": "metal",
      "3d_coords": [
        -6.778881072998047,
        -2.903963804244995,
        0.25
      ],
      "group": [
        [
          -6.778881211249344,
          -2.903963790369886
        ],
        [
          -6.191157553174068,
          -0.2207996798687395
        ],
        [
          -5.759089802648349,
          2.4917832591579074
        ],
        [
          -4.9192066030911255,
          5.107005038136569
        ],
        [
          -4.10696092485864,
          7.730942099183469
        ],
        [
          -3.188925946354106,
          10.319764325676623
        ],
        [
          -2.7422365606297374,
          13.029977847675209
        ],
        [
          -2.3082509010146,
          15.742254601509746
        ]
      ],
      "rotation": 175.99971595095212,
      "color": "cyan",
      "shape": "cube"
    },
    {
      "size": "medium",
      "pixel_coords": [
        123,
        65,
        28.909605026245117
      ],
      "material": "metal",
      "3d_coords": [
        -6.191157341003418,
        -0.22079968452453613,
        0.5
      ],
      "group": [
        [
          -6.778881211249344,
          -2.903963790369886
        ],
        [
          -6.191157553174068,
          -0.2207996798687395
        ],
        [
          -5.759089802648349,
          2.4917832591579074
        ],
        [
          -4.9192066030911255,
          5.107005038136569
        ],
        [
          -4.10696092485864,
          7.730942099183469
        ],
        [
          -3.188925946354106,
          10.319764325676623
        ],
        [
          -2.7422365606297374,
          13.029977847675209
        ],
        [
          -2.3082509010146,
          15.742254601509746
        ]
      ],
      "rotation": 90.55768072340989,
      "color": "cyan",
      "shape": "sphere"
    },
    {
      "size": "medium",
      "pixel_coords": [
        154,
        58,
        29.450952529907227
      ],
      "material": "rubber",
      "3d_coords": [
        -5.759089946746826,
        2.4917831420898438,
        0.5
      ],
      "group": [
        [
          -6.778881211249344,
          -2.903963790369886
        ],
        [
          -6.191157553174068,
          -0.2207996798687395
        ],
        [
          -5.759089802648349,
          2.4917832591579074
        ],
        [
          -4.9192066030911255,
          5.107005038136569
        ],
        [
          -4.10696092485864,
          7.730942099183469
        ],
        [
          -3.188925946354106,
          10.319764325676623
        ],
        [
          -2.7422365606297374,
          13.029977847675209
        ],
        [
          -2.3082509010146,
          15.742254601509746
        ]
      ],
      "rotation": 234.8093116489681,
      "color": "cyan",
      "shape": "sphere"
    },
    {
      "size": "medium",
      "pixel_coords": [
        186,
        54,
        29.742502212524414
      ],
      "material": "metal",
      "3d_coords": [
        -4.919206619262695,
        5.1070051193237305,
        0.5
      ],
      "group": [
        [
          -6.778881211249344,
          -2.903963790369886
        ],
        [
          -6.191157553174068,
          -0.2207996798687395
        ],
        [
          -5.759089802648349,
          2.4917832591579074
        ],
        [
          -4.9192066030911255,
          5.107005038136569
        ],
        [
          -4.10696092485864,
          7.730942099183469
        ],
        [
          -3.188925946354106,
          10.319764325676623
        ],
        [
          -2.7422365606297374,
          13.029977847675209
        ],
        [
          -2.3082509010146,
          15.742254601509746
        ]
      ],
      "rotation": 107.96341902382142,
      "color": "purple",
      "shape": "cone"
    },
    {
      "size": "medium",
      "pixel_coords": [
        217,
        50,
        30.05158805847168
      ],
      "material": "metal",
      "3d_coords": [
        -4.106960773468018,
        7.730942249298096,
        0.5
      ],
      "group": [
        [
          -6.778881211249344,
          -2.903963790369886
        ],
        [
          -6.191157553174068,
          -0.2207996798687395
        ],
        [
          -5.759089802648349,
          2.4917832591579074
        ],
        [
          -4.9192066030911255,
          5.107005038136569
        ],
        [
          -4.10696092485864,
          7.730942099183469
        ],
        [
          -3.188925946354106,
          10.319764325676623
        ],
        [
          -2.7422365606297374,
          13.029977847675209
        ],
        [
          -2.3082509010146,
          15.742254601509746
        ]
      ],
      "rotation": 134.9054135314109,
      "color": "brown",
      "shape": "cone"
    },
    {
      "size": "small",
      "pixel_coords": [
        248,
        48,
        30.411346435546875
      ],
      "material": "metal",
      "3d_coords": [
        -3.1889259815216064,
        10.319764137268066,
        0.3499999940395355
      ],
      "group": [
        [
          -6.778881211249344,
          -2.903963790369886
        ],
        [
          -6.191157553174068,
          -0.2207996798687395
        ],
        [
          -5.759089802648349,
          2.4917832591579074
        ],
        [
          -4.9192066030911255,
          5.107005038136569
        ],
        [
          -4.10696092485864,
          7.730942099183469
        ],
        [
          -3.188925946354106,
          10.319764325676623
        ],
        [
          -2.7422365606297374,
          13.029977847675209
        ],
        [
          -2.3082509010146,
          15.742254601509746
        ]
      ],
      "rotation": 54.119169442979555,
      "color": "brown",
      "shape": "sphere"
    },
    {
      "size": "mini",
      "pixel_coords": [
        276,
        43,
        31.022920608520508
      ],
      "material": "metal",
      "3d_coords": [
        -2.742236614227295,
        13.029977798461914,
        0.25
      ],
      "group": [
        [
          -6.778881211249344,
          -2.903963790369886
        ],
        [
          -6.191157553174068,
          -0.2207996798687395
        ],
        [
          -5.759089802648349,
          2.4917832591579074
        ],
        [
          -4.9192066030911255,
          5.107005038136569
        ],
        [
          -4.10696092485864,
          7.730942099183469
        ],
        [
          -3.188925946354106,
          10.319764325676623
        ],
        [
          -2.7422365606297374,
          13.029977847675209
        ],
        [
          -2.3082509010146,
          15.742254601509746
        ]
      ],
      "rotation": 263.72037899166503,
      "color": "gray",
      "shape": "cylinder"
    },
    {
      "size": "mini",
      "pixel_coords": [
        303,
        36,
        31.56313705444336
      ],
      "material": "rubber",
      "3d_coords": [
        -2.308250904083252,
        15.742254257202148,
        0.25
      ],
      "group": [
        [
          -6.778881211249344,
          -2.903963790369886
        ],
        [
          -6.191157553174068,
          -0.2207996798687395
        ],
        [
          -5.759089802648349,
          2.4917832591579074
        ],
        [
          -4.9192066030911255,
          5.107005038136569
        ],
        [
          -4.10696092485864,
          7.730942099183469
        ],
        [
          -3.188925946354106,
          10.319764325676623
        ],
        [
          -2.7422365606297374,
          13.029977847675209
        ],
        [
          -2.3082509010146,
          15.742254601509746
        ]
      ],
      "rotation": 92.56149284350984,
      "color": "green",
      "shape": "sphere"
    }
  ],
  "image_filename": "CLEVR_new_000187.png",
  "split": "new",
  "relationships": {
    "behind": [
      [
        4,
        5,
        6,
        7,
        8,
        9,
        10,
        11
      ],
      [
        0,
        4,
        5,
        6,
        7,
        8,
        9,
        10,
        11
      ],
      [
        0,
        1,
        4,
        5,
        6,
        7,
        8,
        9,
        10,
        11
      ],
      [
        0,
        1,
        2,
        4,
        5,
        6,
        7,
        8,
        9,
        10,
        11
      ],
      [
        5,
        6,
        7,
        8,
        9,
        10,
        11
      ],
      [
        6,
        7,
        8,
        9,
        10,
        11
      ],
      [
        7,
        8,
        9,
        10,
        11
      ],
      [
        8,
        9,
        10,
        11
      ],
      [
        9,
        10,
        11
      ],
      [
        10,
        11
      ],
      [
        11
      ],
      []
    ],
    "left": [
      [],
      [
        0,
        4
      ],
      [
        0,
        1,
        4,
        5,
        6
      ],
      [
        0,
        1,
        2,
        4,
        5,
        6
      ],
      [
        0
      ],
      [
        0,
        4
      ],
      [
        0,
        1,
        4,
        5
      ],
      [
        0,
        1,
        2,
        3,
        4,
        5,
        6
      ],
      [
        0,
        1,
        2,
        3,
        4,
        5,
        6,
        7
      ],
      [
        0,
        1,
        2,
        3,
        4,
        5,
        6,
        7,
        8
      ],
      [
        0,
        1,
        2,
        3,
        4,
        5,
        6,
        7,
        8,
        9
      ],
      [
        0,
        1,
        2,
        3,
        4,
        5,
        6,
        7,
        8,
        9,
        10
      ]
    ],
    "front": [
      [
        1,
        2,
        3
      ],
      [
        2,
        3
      ],
      [
        3
      ],
      [],
      [
        0,
        1,
        2,
        3
      ],
      [
        0,
        1,
        2,
        3,
        4
      ],
      [
        0,
        1,
        2,
        3,
        4,
        5
      ],
      [
        0,
        1,
        2,
        3,
        4,
        5,
        6
      ],
      [
        0,
        1,
        2,
        3,
        4,
        5,
        6,
        7
      ],
      [
        0,
        1,
        2,
        3,
        4,
        5,
        6,
        7,
        8
      ],
      [
        0,
        1,
        2,
        3,
        4,
        5,
        6,
        7,
        8,
        9
      ],
      [
        0,
        1,
        2,
        3,
        4,
        5,
        6,
        7,
        8,
        9,
        10
      ]
    ],
    "right": [
      [
        1,
        2,
        3,
        4,
        5,
        6,
        7,
        8,
        9,
        10,
        11
      ],
      [
        2,
        3,
        6,
        7,
        8,
        9,
        10,
        11
      ],
      [
        3,
        7,
        8,
        9,
        10,
        11
      ],
      [
        7,
        8,
        9,
        10,
        11
      ],
      [
        1,
        2,
        3,
        5,
        6,
        7,
        8,
        9,
        10,
        11
      ],
      [
        2,
        3,
        6,
        7,
        8,
        9,
        10,
        11
      ],
      [
        2,
        3,
        7,
        8,
        9,
        10,
        11
      ],
      [
        8,
        9,
        10,
        11
      ],
      [
        9,
        10,
        11
      ],
      [
        10,
        11
      ],
      [
        11
      ],
      []
    ]
  },
  "directions": {
    "above": [
      0.0,
      0.0,
      1.0
    ],
    "below": [
      -0.0,
      -0.0,
      -1.0
    ],
    "behind": [
      -0.754490315914154,
      0.6563112735748291,
      0.0
    ],
    "left": [
      -0.6563112735748291,
      -0.7544902563095093,
      0.0
    ],
    "front": [
      0.754490315914154,
      -0.6563112735748291,
      -0.0
    ],
    "right": [
      0.6563112735748291,
      0.7544902563095093,
      -0.0
    ]
  }
}