{
  "image_index": 146,
  "objects": [
    {
      "size": "large",
      "pixel_coords": [
        84,
        78,
        27.918569564819336
      ],
      "material": "metal",
      "3d_coords": [
        -6.015059471130371,
        -3.703184127807617,
        0.699999988079071
      ],
      "group": [
        [
          -6.015059362213121,
          -3.7031842467146348
        ],
        [
          -3.2616270287358176,
          -1.4409031962511336
        ],
        [
          -0.1502435673474789,
          0.29650813170883783
        ],
        [
          2.7540152427667,
          2.361595522159588
        ]
      ],
      "rotation": 81.74088086812988,
      "color": "cyan",
      "shape": "cone"
    },
    {
      "size": "medium",
      "pixel_coords": [
        124,
        93,
        27.22380828857422
      ],
      "material": "rubber",
      "3d_coords": [
        -3.261626958847046,
        -1.4409031867980957,
        0.5
      ],
      "group": [
        [
          -6.015059362213121,
          -3.7031842467146348
        ],
        [
          -3.2616270287358176,
          -1.4409031962511336
        ],
        [
          -0.1502435673474789,
          0.29650813170883783
        ],
        [
          2.7540152427667,
          2.361595522159588
        ]
      ],
      "rotation": 269.26674367574395,
      "color": "blue",
      "shape": "cone"
    },
    {
      "size": "large",
      "pixel_coords": [
        163,
        111,
        25.875484466552734
      ],
      "material": "rubber",
      "3d_coords": [
        -0.15024356544017792,
        0.29650813341140747,
        0.699999988079071
      ],
      "group": [
        [
          -6.015059362213121,
          -3.7031842467146348
        ],
        [
          -3.2616270287358176,
          -1.4409031962511336
        ],
        [
          -0.1502435673474789,
          0.29650813170883783
        ],
        [
          2.7540152427667,
          2.361595522159588
        ]
      ],
      "rotation": 53.32130344986711,
      "color": "yellow",
      "shape": "cone"
    },
    {
      "size": "medium",
      "pixel_coords": [
        207,
        131,
        25.04693031311035
      ],
      "material": "metal",
      "3d_coords": [
        2.7540152072906494,
        2.361595630645752,
        0.5
      ],
      "group": [
        [
          -6.015059362213121,
          -3.7031842467146348
        ],
        [
          -3.2616270287358176,
          -1.4409031962511336
        ],
        [
          -0.1502435673474789,
          0.29650813170883783
        ],
        [
          2.7540152427667,
          2.361595522159588
        ]
      ],
      "rotation": 348.4181939914496,
      "color": "gray",
      "shape": "cone"
    },
    {
      "size": "small",
      "pixel_coords": [
        143,
        102,
        26.88837242126465
      ],
      "material": "rubber",
      "3d_coords": [
        -1.934586763381958,
        -0.5114485621452332,
        0.3499999940395355
      ],
      "group": [
        [
          -1.9345867388467344,
          -0.5114485787874354
        ],
        [
          -0.6002105034834226,
          0.49433414137593124
        ],
        [
          0.660297755236908,
          1.5912743163077394
        ],
        [
          1.6781331638884893,
          2.916479922459726
        ]
      ],
      "rotation": 305.2655555788634,
      "color": "green",
      "shape": "cube"
    },
    {
      "size": "mini",
      "pixel_coords": [
        162,
        110,
        26.52961540222168
      ],
      "material": "metal",
      "3d_coords": [
        -0.6002104878425598,
        0.4943341314792633,
        0.25
      ],
      "group": [
        [
          -1.9345867388467344,
          -0.5114485787874354
        ],
        [
          -0.6002105034834226,
          0.49433414137593124
        ],
        [
          0.660297755236908,
          1.5912743163077394
        ],
        [
          1.6781331638884893,
          2.916479922459726
        ]
      ],
      "rotation": 206.98483089109308,
      "color": "blue",
      "shape": "sphere"
    },
    {
      "size": "small",
      "pixel_coords": [
        183,
        116,
        26.074596405029297
      ],
      "material": "metal",
      "3d_coords": [
        0.6602977514266968,
        1.5912742614746094,
        0.3499999940395355
      ],
      "group": [
        [
          -1.9345867388467344,
          -0.5114485787874354
        ],
        [
          -0.6002105034834226,
          0.49433414137593124
        ],
        [
          0.660297755236908,
          1.5912743163077394
        ],
        [
          1.6781331638884893,
          2.916479922459726
        ]
      ],
      "rotation": 44.614143681039096,
      "color": "purple",
      "shape": "sphere"
    },
    {
      "size": "large",
      "pixel_coords": [
        206,
        116,
        25.610340118408203
      ],
      "material": "metal",
      "3d_coords": [
        1.6781331300735474,
        2.9164798259735107,
        0.699999988079071
      ],
      "group": [
        [
          -1.9345867388467344,
          -0.5114485787874354
        ],
        [
          -0.6002105034834226,
          0.49433414137593124
        ],
        [
          0.660297755236908,
          1.5912743163077394
        ],
        [
          1.6781331638884893,
          2.916479922459726
        ]
      ],
      "rotation": 160.33030797508212,
      "color": "gray",
      "shape": "sphere"
    }
  ],
  "image_filename": "CLEVR_new_000146.png",
  "split": "new",
  "relationships": {
    "behind": [
      [],
      [
        0
      ],
      [
        0,
        1,
        4,
        5,
        6,
        7
      ],
      [
        0,
        1,
        2,
        4,
        5,
        6,
        7
      ],
      [
        0,
        1
      ],
      [
        0,
        1,
        4
      ],
      [
        0,
        1,
        4,
        5
      ],
      [
        0,
        1,
        4
      ]
    ],
    "left": [
      [],
      [
        0
      ],
      [
        0,
        1,
        4
      ],
      [
        0,
        1,
        2,
        4,
        5,
        6,
        7
      ],
      [
        0,
        1
      ],
      [
        0,
        1,
        4
      ],
      [
        0,
        1,
        2,
        4,
        5
      ],
      [
        0,
        1,
        2,
        4,
        5,
        6
      ]
    ],
    "front": [
      [
        1,
        2,
        3,
        4,
        5,
        6,
        7
      ],
      [
        2,
        3,
        4,
        5,
        6,
        7
      ],
      [
        3
      ],
      [],
      [
        2,
        3,
        5,
        6,
        7
      ],
      [
        2,
        3,
        6
      ],
      [
        2,
        3
      ],
      [
        2,
        3
      ]
    ],
    "right": [
      [
        1,
        2,
        3,
        4,
        5,
        6,
        7
      ],
      [
        2,
        3,
        4,
        5,
        6,
        7
      ],
      [
        3,
        6,
        7
      ],
      [],
      [
        2,
        3,
        5,
        6,
        7
      ],
      [
        3,
        6,
        7
      ],
      [
        3,
        7
      ],
      [
        3
      ]
    ]
  },
  "directions": {
    "above": [
      0.0,
      0.0,
      1.0
    ],
    "below": [
      -0.0,
      -0.0,
      -1.0
    ],
    "behind": [
      -0.754490315914154,
      0.6563112735748291,
      0.0
    ],
    "left": [
      -0.6563112735748291,
      -0.7544902563095093,
      0.0
    ],
    "front": [
      0.754490315914154,
      -0.6563112735748291,
      -0.0
    ],
    "right": [
      0.6563112735748291,
      0.7544902563095093,
      -0.0
    ]
  }
}