{
  "image_index": 99,
  "objects": [
    {
      "size": "small",
      "pixel_coords": [
        118,
        84,
        28.405353546142578
      ],
      "material": "rubber",
      "3d_coords": [
        -4.573933124542236,
        -1.532678246498108,
        0.3499999940395355
      ],
      "group": [
        [
          -4.573933135691436,
          -1.5326782322343195
        ],
        [
          -2.283481828038593,
          1.2562604641828785
        ],
        [
          0.5306403242163134,
          3.5156990575706466
        ],
        [
          3.2024492019535282,
          5.94176244626157
        ],
        [
          6.447507336500078,
          7.520985023517589
        ]
      ],
      "rotation": 294.8136305082635,
      "color": "purple",
      "shape": "cylinder"
    },
    {
      "size": "mini",
      "pixel_coords": [
        162,
        92,
        27.967357635498047
      ],
      "material": "rubber",
      "3d_coords": [
        -2.2834818363189697,
        1.2562605142593384,
        0.25
      ],
      "group": [
        [
          -4.573933135691436,
          -1.5326782322343195
        ],
        [
          -2.283481828038593,
          1.2562604641828785
        ],
        [
          0.5306403242163134,
          3.5156990575706466
        ],
        [
          3.2024492019535282,
          5.94176244626157
        ],
        [
          6.447507336500078,
          7.520985023517589
        ]
      ],
      "rotation": 13.377305857076212,
      "color": "cyan",
      "shape": "cone"
    },
    {
      "size": "mini",
      "pixel_coords": [
        204,
        107,
        27.022830963134766
      ],
      "material": "metal",
      "3d_coords": [
        0.5306403040885925,
        3.5156991481781006,
        0.25
      ],
      "group": [
        [
          -4.573933135691436,
          -1.5326782322343195
        ],
        [
          -2.283481828038593,
          1.2562604641828785
        ],
        [
          0.5306403242163134,
          3.5156990575706466
        ],
        [
          3.2024492019535282,
          5.94176244626157
        ],
        [
          6.447507336500078,
          7.520985023517589
        ]
      ],
      "rotation": 248.93404414070582,
      "color": "blue",
      "shape": "cylinder"
    },
    {
      "size": "mini",
      "pixel_coords": [
        250,
        121,
        26.20041275024414
      ],
      "material": "rubber",
      "3d_coords": [
        3.202449083328247,
        5.941762447357178,
        0.25
      ],
      "group": [
        [
          -4.573933135691436,
          -1.5326782322343195
        ],
        [
          -2.283481828038593,
          1.2562604641828785
        ],
        [
          0.5306403242163134,
          3.5156990575706466
        ],
        [
          3.2024492019535282,
          5.94176244626157
        ],
        [
          6.447507336500078,
          7.520985023517589
        ]
      ],
      "rotation": 312.15644587941784,
      "color": "yellow",
      "shape": "cube"
    },
    {
      "size": "large",
      "pixel_coords": [
        297,
        143,
        24.482606887817383
      ],
      "material": "metal",
      "3d_coords": [
        6.447507381439209,
        7.520985126495361,
        0.699999988079071
      ],
      "group": [
        [
          -4.573933135691436,
          -1.5326782322343195
        ],
        [
          -2.283481828038593,
          1.2562604641828785
        ],
        [
          0.5306403242163134,
          3.5156990575706466
        ],
        [
          3.2024492019535282,
          5.94176244626157
        ],
        [
          6.447507336500078,
          7.520985023517589
        ]
      ],
      "rotation": 173.25567281930716,
      "color": "green",
      "shape": "sphere"
    },
    {
      "size": "mini",
      "pixel_coords": [
        110,
        70,
        29.490577697753906
      ],
      "material": "rubber",
      "3d_coords": [
        -6.445957183837891,
        -1.609190583229065,
        0.25
      ],
      "group": [
        [
          -6.445957289747705,
          -1.6091905916571392
        ],
        [
          -5.635175445539712,
          0.9282644013083807
        ],
        [
          -5.029011576745381,
          3.5222209168250256
        ],
        [
          -4.4356057365361945,
          6.119125718512718
        ],
        [
          -4.351014250107443,
          8.78162253928955
        ]
      ],
      "rotation": 8.033922003204012,
      "color": "red",
      "shape": "cube"
    },
    {
      "size": "mini",
      "pixel_coords": [
        141,
        67,
        29.717750549316406
      ],
      "material": "metal",
      "3d_coords": [
        -5.6351752281188965,
        0.9282643795013428,
        0.25
      ],
      "group": [
        [
          -6.445957289747705,
          -1.6091905916571392
        ],
        [
          -5.635175445539712,
          0.9282644013083807
        ],
        [
          -5.029011576745381,
          3.5222209168250256
        ],
        [
          -4.4356057365361945,
          6.119125718512718
        ],
        [
          -4.351014250107443,
          8.78162253928955
        ]
      ],
      "rotation": 61.25308112037378,
      "color": "gray",
      "shape": "sphere"
    },
    {
      "size": "mini",
      "pixel_coords": [
        171,
        62,
        30.072036743164062
      ],
      "material": "metal",
      "3d_coords": [
        -5.0290117263793945,
        3.5222208499908447,
        0.25
      ],
      "group": [
        [
          -6.445957289747705,
          -1.6091905916571392
        ],
        [
          -5.635175445539712,
          0.9282644013083807
        ],
        [
          -5.029011576745381,
          3.5222209168250256
        ],
        [
          -4.4356057365361945,
          6.119125718512718
        ],
        [
          -4.351014250107443,
          8.78162253928955
        ]
      ],
      "rotation": 315.1316466967382,
      "color": "yellow",
      "shape": "cone"
    },
    {
      "size": "large",
      "pixel_coords": [
        202,
        54,
        30.077064514160156
      ],
      "material": "metal",
      "3d_coords": [
        -4.435605525970459,
        6.119125843048096,
        0.699999988079071
      ],
      "group": [
        [
          -6.445957289747705,
          -1.6091905916571392
        ],
        [
          -5.635175445539712,
          0.9282644013083807
        ],
        [
          -5.029011576745381,
          3.5222209168250256
        ],
        [
          -4.4356057365361945,
          6.119125718512718
        ],
        [
          -4.351014250107443,
          8.78162253928955
        ]
      ],
      "rotation": 246.11061686877323,
      "color": "brown",
      "shape": "cube"
    },
    {
      "size": "medium",
      "pixel_coords": [
        228,
        47,
        30.894067764282227
      ],
      "material": "metal",
      "3d_coords": [
        -4.351014137268066,
        8.781622886657715,
        0.5
      ],
      "group": [
        [
          -6.445957289747705,
          -1.6091905916571392
        ],
        [
          -5.635175445539712,
          0.9282644013083807
        ],
        [
          -5.029011576745381,
          3.5222209168250256
        ],
        [
          -4.4356057365361945,
          6.119125718512718
        ],
        [
          -4.351014250107443,
          8.78162253928955
        ]
      ],
      "rotation": 101.49947863119276,
      "color": "red",
      "shape": "cube"
    },
    {
      "size": "small",
      "pixel_coords": [
        96,
        110,
        26.715961456298828
      ],
      "material": "metal",
      "3d_coords": [
        -2.718320608139038,
        -4.072615146636963,
        0.3499999940395355
      ],
      "group": [
        [
          -2.718320663623495,
          -4.0726150704585535
        ],
        [
          -0.6485221773233065,
          -0.9631483877801559
        ],
        [
          0.6227152540418261,
          2.5492303243853947
        ],
        [
          1.8723980477504139,
          6.069335683559499
        ]
      ],
      "rotation": 292.3177872088792,
      "color": "yellow",
      "shape": "cube"
    },
    {
      "size": "medium",
      "pixel_coords": [
        145,
        114,
        26.285398483276367
      ],
      "material": "metal",
      "3d_coords": [
        -0.6485221982002258,
        -0.9631484150886536,
        0.5
      ],
      "group": [
        [
          -2.718320663623495,
          -4.0726150704585535
        ],
        [
          -0.6485221773233065,
          -0.9631483877801559
        ],
        [
          0.6227152540418261,
          2.5492303243853947
        ],
        [
          1.8723980477504139,
          6.069335683559499
        ]
      ],
      "rotation": 216.90907161689216,
      "color": "blue",
      "shape": "sphere"
    },
    {
      "size": "small",
      "pixel_coords": [
        194,
        111,
        26.637222290039062
      ],
      "material": "metal",
      "3d_coords": [
        0.6227152347564697,
        2.5492303371429443,
        0.3499999940395355
      ],
      "group": [
        [
          -2.718320663623495,
          -4.0726150704585535
        ],
        [
          -0.6485221773233065,
          -0.9631483877801559
        ],
        [
          0.6227152540418261,
          2.5492303243853947
        ],
        [
          1.8723980477504139,
          6.069335683559499
        ]
      ],
      "rotation": 327.324778473179,
      "color": "gray",
      "shape": "sphere"
    },
    {
      "size": "medium",
      "pixel_coords": [
        242,
        106,
        26.76488494873047
      ],
      "material": "rubber",
      "3d_coords": [
        1.872398018836975,
        6.069335460662842,
        0.5
      ],
      "group": [
        [
          -2.718320663623495,
          -4.0726150704585535
        ],
        [
          -0.6485221773233065,
          -0.9631483877801559
        ],
        [
          0.6227152540418261,
          2.5492303243853947
        ],
        [
          1.8723980477504139,
          6.069335683559499
        ]
      ],
      "rotation": 202.42615436845782,
      "color": "yellow",
      "shape": "cone"
    }
  ],
  "image_filename": "CLEVR_new_000099.png",
  "split": "new",
  "relationships": {
    "behind": [
      [
        5,
        6,
        7,
        8,
        9
      ],
      [
        5,
        6,
        7,
        8,
        9
      ],
      [
        0,
        1,
        5,
        6,
        7,
        8,
        9,
        13
      ],
      [
        0,
        1,
        2,
        5,
        6,
        7,
        8,
        9,
        13
      ],
      [
        0,
        1,
        2,
        3,
        5,
        6,
        7,
        8,
        9,
        12,
        13
      ],
      [
        6,
        7,
        8,
        9
      ],
      [
        7,
        8,
        9
      ],
      [
        8,
        9
      ],
      [
        9
      ],
      [],
      [
        0,
        1,
        2,
        3,
        4,
        5,
        6,
        7,
        8,
        9,
        11,
        12,
        13
      ],
      [
        0,
        1,
        2,
        3,
        4,
        5,
        6,
        7,
        8,
        9,
        12,
        13
      ],
      [
        0,
        1,
        2,
        3,
        5,
        6,
        7,
        8,
        9,
        13
      ],
      [
        5,
        6,
        7,
        8,
        9
      ]
    ],
    "left": [
      [
        5,
        10
      ],
      [
        0,
        5,
        6,
        10,
        11
      ],
      [
        0,
        1,
        5,
        6,
        7,
        8,
        10,
        11,
        12
      ],
      [
        0,
        1,
        2,
        5,
        6,
        7,
        8,
        9,
        10,
        11,
        12,
        13
      ],
      [
        0,
        1,
        2,
        3,
        5,
        6,
        7,
        8,
        9,
        10,
        11,
        12,
        13
      ],
      [],
      [
        0,
        5,
        10
      ],
      [
        0,
        5,
        6,
        10,
        11
      ],
      [
        0,
        1,
        5,
        6,
        7,
        10,
        11
      ],
      [
        0,
        1,
        2,
        5,
        6,
        7,
        8,
        10,
        11,
        12
      ],
      [
        5
      ],
      [
        0,
        5,
        6,
        10
      ],
      [
        0,
        1,
        5,
        6,
        7,
        8,
        10,
        11
      ],
      [
        0,
        1,
        2,
        5,
        6,
        7,
        8,
        9,
        10,
        11,
        12
      ]
    ],
    "front": [
      [
        2,
        3,
        4,
        10,
        11,
        12
      ],
      [
        2,
        3,
        4,
        10,
        11,
        12
      ],
      [
        3,
        4,
        10,
        11,
        12
      ],
      [
        4,
        10,
        11,
        12
      ],
      [
        10,
        11
      ],
      [
        0,
        1,
        2,
        3,
        4,
        10,
        11,
        12,
        13
      ],
      [
        0,
        1,
        2,
        3,
        4,
        5,
        10,
        11,
        12,
        13
      ],
      [
        0,
        1,
        2,
        3,
        4,
        5,
        6,
        10,
        11,
        12,
        13
      ],
      [
        0,
        1,
        2,
        3,
        4,
        5,
        6,
        7,
        10,
        11,
        12,
        13
      ],
      [
        0,
        1,
        2,
        3,
        4,
        5,
        6,
        7,
        8,
        10,
        11,
        12,
        13
      ],
      [],
      [
        10
      ],
      [
        4,
        10,
        11
      ],
      [
        2,
        3,
        4,
        10,
        11,
        12
      ]
    ],
    "right": [
      [
        1,
        2,
        3,
        4,
        6,
        7,
        8,
        9,
        11,
        12,
        13
      ],
      [
        2,
        3,
        4,
        8,
        9,
        12,
        13
      ],
      [
        3,
        4,
        9,
        13
      ],
      [
        4
      ],
      [],
      [
        0,
        1,
        2,
        3,
        4,
        6,
        7,
        8,
        9,
        10,
        11,
        12,
        13
      ],
      [
        1,
        2,
        3,
        4,
        7,
        8,
        9,
        11,
        12,
        13
      ],
      [
        2,
        3,
        4,
        8,
        9,
        12,
        13
      ],
      [
        2,
        3,
        4,
        9,
        12,
        13
      ],
      [
        3,
        4,
        13
      ],
      [
        0,
        1,
        2,
        3,
        4,
        6,
        7,
        8,
        9,
        11,
        12,
        13
      ],
      [
        1,
        2,
        3,
        4,
        7,
        8,
        9,
        12,
        13
      ],
      [
        2,
        3,
        4,
        9,
        13
      ],
      [
        3,
        4
      ]
    ]
  },
  "directions": {
    "above": [
      0.0,
      0.0,
      1.0
    ],
    "below": [
      -0.0,
      -0.0,
      -1.0
    ],
    "behind": [
      -0.754490315914154,
      0.6563112735748291,
      0.0
    ],
    "left": [
      -0.6563112735748291,
      -0.7544902563095093,
      0.0
    ],
    "front": [
      0.754490315914154,
      -0.6563112735748291,
      -0.0
    ],
    "right": [
      0.6563112735748291,
      0.7544902563095093,
      -0.0
    ]
  }
}