{
  "image_index": 227,
  "objects": [
    {
      "size": "medium",
      "pixel_coords": [
        61,
        122,
        26.005037307739258
      ],
      "material": "metal",
      "3d_coords": [
        -2.697028875350952,
        -6.849736213684082,
        0.5
      ],
      "group": [
        [
          -2.6970288448232154,
          -6.8497363985564
        ],
        [
          -2.486789847532223,
          -5.200030649770161
        ],
        [
          -1.8347929948936814,
          -3.6701190190836943
        ],
        [
          -1.2774703233825364,
          -2.1032364665674033
        ],
        [
          -0.8699880296144,
          -0.4908817680516746
        ],
        [
          -0.42185937918421335,
          1.110651936315457
        ],
        [
          -0.3343445853541058,
          2.77139594260335
        ],
        [
          -0.4850020121779144,
          4.427606023874176
        ]
      ],
      "rotation": 42.02854203173333,
      "color": "cyan",
      "shape": "sphere"
    },
    {
      "size": "large",
      "pixel_coords": [
        83,
        114,
        26.169750213623047
      ],
      "material": "metal",
      "3d_coords": [
        -2.4867899417877197,
        -5.20003080368042,
        0.699999988079071
      ],
      "group": [
        [
          -2.6970288448232154,
          -6.8497363985564
        ],
        [
          -2.486789847532223,
          -5.200030649770161
        ],
        [
          -1.8347929948936814,
          -3.6701190190836943
        ],
        [
          -1.2774703233825364,
          -2.1032364665674033
        ],
        [
          -0.8699880296144,
          -0.4908817680516746
        ],
        [
          -0.42185937918421335,
          1.110651936315457
        ],
        [
          -0.3343445853541058,
          2.77139594260335
        ],
        [
          -0.4850020121779144,
          4.427606023874176
        ]
      ],
      "rotation": 312.39873743402285,
      "color": "purple",
      "shape": "sphere"
    },
    {
      "size": "small",
      "pixel_coords": [
        106,
        117,
        26.493370056152344
      ],
      "material": "rubber",
      "3d_coords": [
        -1.834792971611023,
        -3.670119047164917,
        0.3499999940395355
      ],
      "group": [
        [
          -2.6970288448232154,
          -6.8497363985564
        ],
        [
          -2.486789847532223,
          -5.200030649770161
        ],
        [
          -1.8347929948936814,
          -3.6701190190836943
        ],
        [
          -1.2774703233825364,
          -2.1032364665674033
        ],
        [
          -0.8699880296144,
          -0.4908817680516746
        ],
        [
          -0.42185937918421335,
          1.110651936315457
        ],
        [
          -0.3343445853541058,
          2.77139594260335
        ],
        [
          -0.4850020121779144,
          4.427606023874176
        ]
      ],
      "rotation": 88.50435325767906,
      "color": "blue",
      "shape": "cube"
    },
    {
      "size": "medium",
      "pixel_coords": [
        128,
        113,
        26.48396110534668
      ],
      "material": "metal",
      "3d_coords": [
        -1.277470350265503,
        -2.103236436843872,
        0.5
      ],
      "group": [
        [
          -2.6970288448232154,
          -6.8497363985564
        ],
        [
          -2.486789847532223,
          -5.200030649770161
        ],
        [
          -1.8347929948936814,
          -3.6701190190836943
        ],
        [
          -1.2774703233825364,
          -2.1032364665674033
        ],
        [
          -0.8699880296144,
          -0.4908817680516746
        ],
        [
          -0.42185937918421335,
          1.110651936315457
        ],
        [
          -0.3343445853541058,
          2.77139594260335
        ],
        [
          -0.4850020121779144,
          4.427606023874176
        ]
      ],
      "rotation": 168.18539043697916,
      "color": "green",
      "shape": "cone"
    },
    {
      "size": "medium",
      "pixel_coords": [
        149,
        110,
        26.687902450561523
      ],
      "material": "rubber",
      "3d_coords": [
        -0.8699880242347717,
        -0.4908817708492279,
        0.5
      ],
      "group": [
        [
          -2.6970288448232154,
          -6.8497363985564
        ],
        [
          -2.486789847532223,
          -5.200030649770161
        ],
        [
          -1.8347929948936814,
          -3.6701190190836943
        ],
        [
          -1.2774703233825364,
          -2.1032364665674033
        ],
        [
          -0.8699880296144,
          -0.4908817680516746
        ],
        [
          -0.42185937918421335,
          1.110651936315457
        ],
        [
          -0.3343445853541058,
          2.77139594260335
        ],
        [
          -0.4850020121779144,
          4.427606023874176
        ]
      ],
      "rotation": 348.23224765240604,
      "color": "purple",
      "shape": "cube"
    },
    {
      "size": "mini",
      "pixel_coords": [
        171,
        109,
        27.0640926361084
      ],
      "material": "rubber",
      "3d_coords": [
        -0.42185938358306885,
        1.110651969909668,
        0.25
      ],
      "group": [
        [
          -2.6970288448232154,
          -6.8497363985564
        ],
        [
          -2.486789847532223,
          -5.200030649770161
        ],
        [
          -1.8347929948936814,
          -3.6701190190836943
        ],
        [
          -1.2774703233825364,
          -2.1032364665674033
        ],
        [
          -0.8699880296144,
          -0.4908817680516746
        ],
        [
          -0.42185937918421335,
          1.110651936315457
        ],
        [
          -0.3343445853541058,
          2.77139594260335
        ],
        [
          -0.4850020121779144,
          4.427606023874176
        ]
      ],
      "rotation": 242.26266980403562,
      "color": "gray",
      "shape": "cube"
    },
    {
      "size": "large",
      "pixel_coords": [
        190,
        99,
        27.101924896240234
      ],
      "material": "rubber",
      "3d_coords": [
        -0.3343445956707001,
        2.7713959217071533,
        0.699999988079071
      ],
      "group": [
        [
          -2.6970288448232154,
          -6.8497363985564
        ],
        [
          -2.486789847532223,
          -5.200030649770161
        ],
        [
          -1.8347929948936814,
          -3.6701190190836943
        ],
        [
          -1.2774703233825364,
          -2.1032364665674033
        ],
        [
          -0.8699880296144,
          -0.4908817680516746
        ],
        [
          -0.42185937918421335,
          1.110651936315457
        ],
        [
          -0.3343445853541058,
          2.77139594260335
        ],
        [
          -0.4850020121779144,
          4.427606023874176
        ]
      ],
      "rotation": 200.01109902999897,
      "color": "yellow",
      "shape": "sphere"
    },
    {
      "size": "small",
      "pixel_coords": [
        207,
        94,
        27.902233123779297
      ],
      "material": "metal",
      "3d_coords": [
        -0.4850020110607147,
        4.427606105804443,
        0.3499999940395355
      ],
      "group": [
        [
          -2.6970288448232154,
          -6.8497363985564
        ],
        [
          -2.486789847532223,
          -5.200030649770161
        ],
        [
          -1.8347929948936814,
          -3.6701190190836943
        ],
        [
          -1.2774703233825364,
          -2.1032364665674033
        ],
        [
          -0.8699880296144,
          -0.4908817680516746
        ],
        [
          -0.42185937918421335,
          1.110651936315457
        ],
        [
          -0.3343445853541058,
          2.77139594260335
        ],
        [
          -0.4850020121779144,
          4.427606023874176
        ]
      ],
      "rotation": 320.4517019390421,
      "color": "gray",
      "shape": "sphere"
    },
    {
      "size": "medium",
      "pixel_coords": [
        129,
        79,
        28.740041732788086
      ],
      "material": "rubber",
      "3d_coords": [
        -4.65341854095459,
        -0.6278963088989258,
        0.5
      ],
      "group": [
        [
          -4.653418324208404,
          -0.6278962994700681
        ],
        [
          -1.926450974117587,
          -0.16125013581560305
        ],
        [
          0.7515645414899534,
          0.5332586608745786
        ],
        [
          3.1300235012410305,
          1.946426218984581
        ],
        [
          5.290927210736395,
          3.6740270782121787
        ],
        [
          7.599943986866043,
          5.198018908264626
        ]
      ],
      "rotation": 149.0387639476674,
      "color": "gray",
      "shape": "cube"
    },
    {
      "size": "mini",
      "pixel_coords": [
        148,
        101,
        27.556352615356445
      ],
      "material": "metal",
      "3d_coords": [
        -1.9264509677886963,
        -0.16125012934207916,
        0.25
      ],
      "group": [
        [
          -4.653418324208404,
          -0.6278962994700681
        ],
        [
          -1.926450974117587,
          -0.16125013581560305
        ],
        [
          0.7515645414899534,
          0.5332586608745786
        ],
        [
          3.1300235012410305,
          1.946426218984581
        ],
        [
          5.290927210736395,
          3.6740270782121787
        ],
        [
          7.599943986866043,
          5.198018908264626
        ]
      ],
      "rotation": 202.34743844117418,
      "color": "red",
      "shape": "sphere"
    },
    {
      "size": "mini",
      "pixel_coords": [
        171,
        123,
        26.26273536682129
      ],
      "material": "metal",
      "3d_coords": [
        0.7515645623207092,
        0.5332586765289307,
        0.25
      ],
      "group": [
        [
          -4.653418324208404,
          -0.6278962994700681
        ],
        [
          -1.926450974117587,
          -0.16125013581560305
        ],
        [
          0.7515645414899534,
          0.5332586608745786
        ],
        [
          3.1300235012410305,
          1.946426218984581
        ],
        [
          5.290927210736395,
          3.6740270782121787
        ],
        [
          7.599943986866043,
          5.198018908264626
        ]
      ],
      "rotation": 264.2504028233433,
      "color": "red",
      "shape": "cylinder"
    },
    {
      "size": "mini",
      "pixel_coords": [
        203,
        139,
        25.325645446777344
      ],
      "material": "rubber",
      "3d_coords": [
        3.13002347946167,
        1.946426272392273,
        0.25
      ],
      "group": [
        [
          -4.653418324208404,
          -0.6278962994700681
        ],
        [
          -1.926450974117587,
          -0.16125013581560305
        ],
        [
          0.7515645414899534,
          0.5332586608745786
        ],
        [
          3.1300235012410305,
          1.946426218984581
        ],
        [
          5.290927210736395,
          3.6740270782121787
        ],
        [
          7.599943986866043,
          5.198018908264626
        ]
      ],
      "rotation": 189.37935425798116,
      "color": "blue",
      "shape": "cube"
    },
    {
      "size": "mini",
      "pixel_coords": [
        240,
        153,
        24.59229278564453
      ],
      "material": "rubber",
      "3d_coords": [
        5.290927410125732,
        3.6740269660949707,
        0.25
      ],
      "group": [
        [
          -4.653418324208404,
          -0.6278962994700681
        ],
        [
          -1.926450974117587,
          -0.16125013581560305
        ],
        [
          0.7515645414899534,
          0.5332586608745786
        ],
        [
          3.1300235012410305,
          1.946426218984581
        ],
        [
          5.290927210736395,
          3.6740270782121787
        ],
        [
          7.599943986866043,
          5.198018908264626
        ]
      ],
      "rotation": 98.41617785397241,
      "color": "cyan",
      "shape": "cylinder"
    },
    {
      "size": "medium",
      "pixel_coords": [
        279,
        169,
        23.525453567504883
      ],
      "material": "rubber",
      "3d_coords": [
        7.599944114685059,
        5.198019027709961,
        0.5
      ],
      "group": [
        [
          -4.653418324208404,
          -0.6278962994700681
        ],
        [
          -1.926450974117587,
          -0.16125013581560305
        ],
        [
          0.7515645414899534,
          0.5332586608745786
        ],
        [
          3.1300235012410305,
          1.946426218984581
        ],
        [
          5.290927210736395,
          3.6740270782121787
        ],
        [
          7.599943986866043,
          5.198018908264626
        ]
      ],
      "rotation": 173.57929762456908,
      "color": "brown",
      "shape": "cone"
    }
  ],
  "image_filename": "CLEVR_new_000227.png",
  "split": "new",
  "relationships": {
    "behind": [
      [
        1,
        2,
        3,
        4,
        5,
        6,
        7,
        8,
        9,
        10,
        11,
        12
      ],
      [
        2,
        3,
        4,
        5,
        6,
        7,
        8,
        9,
        10,
        11
      ],
      [
        3,
        4,
        5,
        6,
        7,
        8,
        9,
        10
      ],
      [
        4,
        5,
        6,
        7,
        8,
        9
      ],
      [
        5,
        6,
        7,
        8,
        9
      ],
      [
        6,
        7,
        8,
        9
      ],
      [
        7,
        8
      ],
      [],
      [],
      [
        6,
        7,
        8
      ],
      [
        4,
        5,
        6,
        7,
        8,
        9
      ],
      [
        3,
        4,
        5,
        6,
        7,
        8,
        9,
        10
      ],
      [
        2,
        3,
        4,
        5,
        6,
        7,
        8,
        9,
        10,
        11
      ],
      [
        1,
        2,
        3,
        4,
        5,
        6,
        7,
        8,
        9,
        10,
        11,
        12
      ]
    ],
    "left": [
      [],
      [
        0
      ],
      [
        0,
        1
      ],
      [
        0,
        1,
        2,
        8
      ],
      [
        0,
        1,
        2,
        3,
        8,
        9
      ],
      [
        0,
        1,
        2,
        3,
        4,
        8,
        9
      ],
      [
        0,
        1,
        2,
        3,
        4,
        5,
        8,
        9,
        10
      ],
      [
        0,
        1,
        2,
        3,
        4,
        5,
        6,
        8,
        9,
        10
      ],
      [
        0,
        1,
        2
      ],
      [
        0,
        1,
        2,
        3,
        8
      ],
      [
        0,
        1,
        2,
        3,
        4,
        5,
        8,
        9
      ],
      [
        0,
        1,
        2,
        3,
        4,
        5,
        6,
        7,
        8,
        9,
        10
      ],
      [
        0,
        1,
        2,
        3,
        4,
        5,
        6,
        7,
        8,
        9,
        10,
        11
      ],
      [
        0,
        1,
        2,
        3,
        4,
        5,
        6,
        7,
        8,
        9,
        10,
        11,
        12
      ]
    ],
    "front": [
      [],
      [
        0,
        13
      ],
      [
        0,
        1,
        12,
        13
      ],
      [
        0,
        1,
        2,
        11,
        12,
        13
      ],
      [
        0,
        1,
        2,
        3,
        10,
        11,
        12,
        13
      ],
      [
        0,
        1,
        2,
        3,
        4,
        10,
        11,
        12,
        13
      ],
      [
        0,
        1,
        2,
        3,
        4,
        5,
        9,
        10,
        11,
        12,
        13
      ],
      [
        0,
        1,
        2,
        3,
        4,
        5,
        6,
        9,
        10,
        11,
        12,
        13
      ],
      [
        0,
        1,
        2,
        3,
        4,
        5,
        6,
        9,
        10,
        11,
        12,
        13
      ],
      [
        0,
        1,
        2,
        3,
        4,
        5,
        10,
        11,
        12,
        13
      ],
      [
        0,
        1,
        2,
        11,
        12,
        13
      ],
      [
        0,
        1,
        12,
        13
      ],
      [
        0,
        13
      ],
      []
    ],
    "right": [
      [
        1,
        2,
        3,
        4,
        5,
        6,
        7,
        8,
        9,
        10,
        11,
        12,
        13
      ],
      [
        2,
        3,
        4,
        5,
        6,
        7,
        8,
        9,
        10,
        11,
        12,
        13
      ],
      [
        3,
        4,
        5,
        6,
        7,
        8,
        9,
        10,
        11,
        12,
        13
      ],
      [
        4,
        5,
        6,
        7,
        9,
        10,
        11,
        12,
        13
      ],
      [
        5,
        6,
        7,
        10,
        11,
        12,
        13
      ],
      [
        6,
        7,
        10,
        11,
        12,
        13
      ],
      [
        7,
        11,
        12,
        13
      ],
      [
        11,
        12,
        13
      ],
      [
        3,
        4,
        5,
        6,
        7,
        9,
        10,
        11,
        12,
        13
      ],
      [
        4,
        5,
        6,
        7,
        10,
        11,
        12,
        13
      ],
      [
        6,
        7,
        11,
        12,
        13
      ],
      [
        12,
        13
      ],
      [
        13
      ],
      []
    ]
  },
  "directions": {
    "above": [
      0.0,
      0.0,
      1.0
    ],
    "below": [
      -0.0,
      -0.0,
      -1.0
    ],
    "behind": [
      -0.754490315914154,
      0.6563112735748291,
      0.0
    ],
    "left": [
      -0.6563112735748291,
      -0.7544902563095093,
      0.0
    ],
    "front": [
      0.754490315914154,
      -0.6563112735748291,
      -0.0
    ],
    "right": [
      0.6563112735748291,
      0.7544902563095093,
      -0.0
    ]
  }
}