{
  "image_filename": "CLEVR_new_000068.png",
  "split": "new",
  "objects": [
    {
      "shape": "cube",
      "material": "metal",
      "group": 0,
      "size": "small",
      "pixel_coords": [
        227,
        90,
        27.947772979736328
      ],
      "3d_coords": [
        0.08402588963508606,
        5.98655366897583,
        0.3499999940395355
      ],
      "rotation": 138.15121236529606,
      "color": "brown"
    },
    {
      "shape": "sphere",
      "material": "rubber",
      "group": 0,
      "size": "large",
      "pixel_coords": [
        249,
        83,
        27.933143615722656
      ],
      "3d_coords": [
        0.5155444145202637,
        7.7718963623046875,
        0.699999988079071
      ],
      "rotation": 341.28496472740795,
      "color": "yellow"
    },
    {
      "shape": "cylinder",
      "material": "rubber",
      "group": 0,
      "size": "medium",
      "pixel_coords": [
        210,
        84,
        28.160982131958008
      ],
      "3d_coords": [
        -1.0297011137008667,
        5.058431148529053,
        0.5
      ],
      "rotation": 266.9818687444437,
      "color": "green"
    },
    {
      "shape": "sphere",
      "material": "metal",
      "group": 1,
      "size": "large",
      "pixel_coords": [
        162,
        98,
        27.032405853271484
      ],
      "3d_coords": [
        -1.3937665224075317,
        0.8666213154792786,
        0.699999988079071
      ],
      "rotation": 319.85802241601635,
      "color": "gray"
    },
    {
      "shape": "cylinder",
      "material": "rubber",
      "group": 1,
      "size": "large",
      "pixel_coords": [
        134,
        87,
        27.691110610961914
      ],
      "3d_coords": [
        -3.3958680629730225,
        -0.587580144405365,
        0.699999988079071
      ],
      "rotation": 319.83907622353917,
      "color": "red"
    },
    {
      "shape": "cone",
      "material": "rubber",
      "group": 1,
      "size": "large",
      "pixel_coords": [
        139,
        107,
        26.488821029663086
      ],
      "3d_coords": [
        -1.3859941959381104,
        -1.080522060394287,
        0.699999988079071
      ],
      "rotation": 234.5833631822041,
      "color": "green"
    },
    {
      "shape": "cube",
      "material": "rubber",
      "group": 2,
      "size": "medium",
      "pixel_coords": [
        153,
        222,
        21.35544776916504
      ],
      "3d_coords": [
        6.9968647956848145,
        -4.143800258636475,
        0.5
      ],
      "rotation": 134.2994742647184,
      "color": "green"
    },
    {
      "shape": "cone",
      "material": "metal",
      "group": 3,
      "size": "small",
      "pixel_coords": [
        217,
        177,
        23.343164443969727
      ],
      "3d_coords": [
        6.1987128257751465,
        1.0692956447601318,
        0.3499999940395355
      ],
      "rotation": 334.8137811428561,
      "color": "blue"
    },
    {
      "shape": "cone",
      "material": "rubber",
      "group": 3,
      "size": "medium",
      "pixel_coords": [
        221,
        160,
        23.95508575439453
      ],
      "3d_coords": [
        5.285080909729004,
        1.9632360935211182,
        0.5
      ],
      "rotation": 267.0090349611343,
      "color": "brown"
    },
    {
      "shape": "cube",
      "material": "metal",
      "group": 3,
      "size": "large",
      "pixel_coords": [
        244,
        177,
        22.96463394165039
      ],
      "3d_coords": [
        7.1131439208984375,
        2.4653923511505127,
        0.699999988079071
      ],
      "rotation": 192.51427875803302,
      "color": "red"
    }
  ],
  "directions": {
    "front": [
      0.754490315914154,
      -0.6563112735748291,
      -0.0
    ],
    "below": [
      -0.0,
      -0.0,
      -1.0
    ],
    "left": [
      -0.6563112735748291,
      -0.7544902563095093,
      0.0
    ],
    "right": [
      0.6563112735748291,
      0.7544902563095093,
      -0.0
    ],
    "behind": [
      -0.754490315914154,
      0.6563112735748291,
      0.0
    ],
    "above": [
      0.0,
      0.0,
      1.0
    ]
  },
  "image_index": 68,
  "relationships": {
    "front": [
      [
        3,
        4,
        5,
        6,
        7,
        8,
        9
      ],
      [
        0,
        2,
        3,
        4,
        5,
        6,
        7,
        8,
        9
      ],
      [
        0,
        3,
        4,
        5,
        6,
        7,
        8,
        9
      ],
      [
        5,
        6,
        7,
        8,
        9
      ],
      [
        3,
        5,
        6,
        7,
        8,
        9
      ],
      [
        6,
        7,
        8,
        9
      ],
      [],
      [
        6
      ],
      [
        6,
        7,
        9
      ],
      [
        6,
        7
      ]
    ],
    "behind": [
      [
        1,
        2
      ],
      [],
      [
        1
      ],
      [
        0,
        1,
        2,
        4
      ],
      [
        0,
        1,
        2
      ],
      [
        0,
        1,
        2,
        3,
        4
      ],
      [
        0,
        1,
        2,
        3,
        4,
        5,
        7,
        8,
        9
      ],
      [
        0,
        1,
        2,
        3,
        4,
        5,
        8,
        9
      ],
      [
        0,
        1,
        2,
        3,
        4,
        5
      ],
      [
        0,
        1,
        2,
        3,
        4,
        5,
        8
      ]
    ],
    "right": [
      [
        1,
        7,
        8,
        9
      ],
      [
        9
      ],
      [
        0,
        1,
        7,
        8,
        9
      ],
      [
        0,
        1,
        2,
        6,
        7,
        8,
        9
      ],
      [
        0,
        1,
        2,
        3,
        5,
        6,
        7,
        8,
        9
      ],
      [
        0,
        1,
        2,
        3,
        6,
        7,
        8,
        9
      ],
      [
        0,
        1,
        2,
        7,
        8,
        9
      ],
      [
        1,
        9
      ],
      [
        1,
        9
      ],
      []
    ],
    "left": [
      [
        2,
        3,
        4,
        5,
        6
      ],
      [
        0,
        2,
        3,
        4,
        5,
        6,
        7,
        8
      ],
      [
        3,
        4,
        5,
        6
      ],
      [
        4,
        5
      ],
      [],
      [
        4
      ],
      [
        3,
        4,
        5
      ],
      [
        0,
        2,
        3,
        4,
        5,
        6
      ],
      [
        0,
        2,
        3,
        4,
        5,
        6
      ],
      [
        0,
        1,
        2,
        3,
        4,
        5,
        6,
        7,
        8
      ]
    ]
  }
}